Crea_library/__init__.py
Crea_library/crea_library.py
Crea_library-0.4.dist-info/METADATA
Crea_library-0.4.dist-info/WHEEL
Crea_library-0.4.dist-info/top_level.txt
Crea_library-0.4.dist-info/RECORD
