Metadata-Version: 2.1
Name: Crea-library
Version: 0.4
Summary: A package to parse CREA word vectors
Home-page: https://github.com/askitowski1/CREA-Vectors/tree/main/crea_library
Author: Alex Skitowski
Author-email: Alex Skitowski <alexskit@gmail.com>
Requires-Dist: numpy
Requires-Dist: scikit-learn
Requires-Dist: scipy
